sepsesam/__init__.py
sepsesam/api.py
sepsesam-0.5.3.dist-info/LICENSE
sepsesam-0.5.3.dist-info/METADATA
sepsesam-0.5.3.dist-info/WHEEL
sepsesam-0.5.3.dist-info/top_level.txt
sepsesam-0.5.3.dist-info/RECORD
