Metadata-Version: 2.1
Name: sepsesam
Version: 0.5.3
Summary: SEP Sesam Python API
Home-page: https://github.com/SAPUCC/sepsesam
Author: SAP UCC Magdeburg
Project-URL: Bug Tracker, https://github.com/SAPUCC/sepsesam/issues
Classifier: Programming Language :: Python :: 3
Classifier: License :: OSI Approved :: MIT License
Classifier: Operating System :: OS Independent
Requires-Python: >=3.6
License-File: LICENSE
